pystac_io/__init__.py
pystac_io/https/__init__.py
pystac_io/s3/__init__.py
pystac_io-0.1.0.dist-info/LICENSE
pystac_io-0.1.0.dist-info/METADATA
pystac_io-0.1.0.dist-info/WHEEL
pystac_io-0.1.0.dist-info/top_level.txt
pystac_io-0.1.0.dist-info/RECORD
